{
    "data": [
        {
            "id": 76398288,
            "system_id": "id",
            "legacy_id": 76398288,
            "driver_id": 1252627,
            "vehicle_number": null,
            "zone_id": 28232,
            "hub_id": 1344,
            "datetime": "2025-01-21T17:00:00Z",
            "date": "2025-01-22",
            "archived": false,
            "estimated_end_time": null,
            "driver_assign_time": "2025-01-22T05:22:23Z",
            "driver_attendance": -1,
            "route_comments": null,
            "outbound_comments": null,
            "is_ok": null,
            "status": "IN_PROGRESS",
            "route_password": "28467377",
            "created_at": "2025-01-21T23:14:43Z",
            "updated_at": "2025-01-22T05:22:23Z",
            "deleted_at": null
        },
        {
            "id": 76398289,
            "system_id": "id",
            "legacy_id": 76398289,
            "driver_id": 1413639,
            "vehicle_number": null,
            "zone_id": 30956,
            "hub_id": 1344,
            "datetime": "2025-01-21T17:00:00Z",
            "date": "2025-01-22",
            "archived": false,
            "estimated_end_time": null,
            "driver_assign_time": "2025-01-22T00:06:32Z",
            "driver_attendance": -1,
            "route_comments": null,
            "outbound_comments": null,
            "is_ok": null,
            "status": "IN_PROGRESS",
            "route_password": "28467376",
            "created_at": "2025-01-21T23:14:43Z",
            "updated_at": "2025-01-22T00:06:32Z",
            "deleted_at": null
        },
        {
            "id": 76398290,
            "system_id": "id",
            "legacy_id": 76398290,
            "driver_id": 1436842,
            "vehicle_number": null,
            "zone_id": 28236,
            "hub_id": 1344,
            "datetime": "2025-01-21T17:00:00Z",
            "date": "2025-01-22",
            "archived": false,
            "estimated_end_time": null,
            "driver_assign_time": "2025-01-22T02:17:05Z",
            "driver_attendance": -1,
            "route_comments": null,
            "outbound_comments": null,
            "is_ok": null,
            "status": "IN_PROGRESS",
            "route_password": "28467365",
            "created_at": "2025-01-21T23:14:43Z",
            "updated_at": "2025-01-22T02:17:05Z",
            "deleted_at": null
        },
        {
            "id": 76398291,
            "system_id": "id",
            "legacy_id": 76398291,
            "driver_id": 1468190,
            "vehicle_number": null,
            "zone_id": 28228,
            "hub_id": 1344,
            "datetime": "2025-01-21T17:00:00Z",
            "date": "2025-01-22",
            "archived": false,
            "estimated_end_time": null,
            "driver_assign_time": "2025-01-22T02:23:29Z",
            "driver_attendance": -1,
            "route_comments": null,
            "outbound_comments": null,
            "is_ok": null,
            "status": "IN_PROGRESS",
            "route_password": "28467360",
            "created_at": "2025-01-21T23:14:43Z",
            "updated_at": "2025-01-22T02:23:29Z",
            "deleted_at": null
        },
        {
            "id": 76398292,
            "system_id": "id",
            "legacy_id": 76398292,
            "driver_id": 1500717,
            "vehicle_number": null,
            "zone_id": 28232,
            "hub_id": 1344,
            "datetime": "2025-01-21T17:00:00Z",
            "date": "2025-01-22",
            "archived": false,
            "estimated_end_time": null,
            "driver_assign_time": "2025-01-22T05:02:16Z",
            "driver_attendance": -1,
            "route_comments": null,
            "outbound_comments": null,
            "is_ok": null,
            "status": "IN_PROGRESS",
            "route_password": "28467363",
            "created_at": "2025-01-21T23:14:43Z",
            "updated_at": "2025-01-22T05:02:16Z",
            "deleted_at": null
        },
        {
            "id": 76398293,
            "system_id": "id",
            "legacy_id": 76398293,
            "driver_id": 1501040,
            "vehicle_number": null,
            "zone_id": 28236,
            "hub_id": 1344,
            "datetime": "2025-01-21T17:00:00Z",
            "date": "2025-01-22",
            "archived": false,
            "estimated_end_time": null,
            "driver_assign_time": null,
            "driver_attendance": -1,
            "route_comments": null,
            "outbound_comments": null,
            "is_ok": null,
            "status": "PENDING",
            "route_password": "28467364",
            "created_at": "2025-01-21T23:14:43Z",
            "updated_at": "2025-01-21T23:14:43Z",
            "deleted_at": null
        },
        {
            "id": 76398294,
            "system_id": "id",
            "legacy_id": 76398294,
            "driver_id": 1532853,
            "vehicle_number": null,
            "zone_id": 28212,
            "hub_id": 1344,
            "datetime": "2025-01-21T17:00:00Z",
            "date": "2025-01-22",
            "archived": false,
            "estimated_end_time": null,
            "driver_assign_time": "2025-01-22T02:10:56Z",
            "driver_attendance": -1,
            "route_comments": null,
            "outbound_comments": null,
            "is_ok": null,
            "status": "IN_PROGRESS",
            "route_password": "28467369",
            "created_at": "2025-01-21T23:14:43Z",
            "updated_at": "2025-01-22T02:10:56Z",
            "deleted_at": null
        },
        {
            "id": 76398295,
            "system_id": "id",
            "legacy_id": 76398295,
            "driver_id": 1704107,
            "vehicle_number": null,
            "zone_id": 28244,
            "hub_id": 1344,
            "datetime": "2025-01-21T17:00:00Z",
            "date": "2025-01-22",
            "archived": false,
            "estimated_end_time": null,
            "driver_assign_time": "2025-01-22T03:55:13Z",
            "driver_attendance": -1,
            "route_comments": null,
            "outbound_comments": null,
            "is_ok": null,
            "status": "IN_PROGRESS",
            "route_password": "28467361",
            "created_at": "2025-01-21T23:14:43Z",
            "updated_at": "2025-01-22T03:55:13Z",
            "deleted_at": null
        },
        {
            "id": 76398296,
            "system_id": "id",
            "legacy_id": 76398296,
            "driver_id": 1554893,
            "vehicle_number": null,
            "zone_id": 28230,
            "hub_id": 1344,
            "datetime": "2025-01-21T17:00:00Z",
            "date": "2025-01-22",
            "archived": false,
            "estimated_end_time": null,
            "driver_assign_time": null,
            "driver_attendance": -1,
            "route_comments": null,
            "outbound_comments": null,
            "is_ok": null,
            "status": "PENDING",
            "route_password": "28467368",
            "created_at": "2025-01-21T23:14:43Z",
            "updated_at": "2025-01-21T23:14:43Z",
            "deleted_at": null
        },
        {
            "id": 76398297,
            "system_id": "id",
            "legacy_id": 76398297,
            "driver_id": 1555403,
            "vehicle_number": null,
            "zone_id": 28224,
            "hub_id": 1344,
            "datetime": "2025-01-21T17:00:00Z",
            "date": "2025-01-22",
            "archived": false,
            "estimated_end_time": null,
            "driver_assign_time": "2025-01-22T02:28:45Z",
            "driver_attendance": -1,
            "route_comments": null,
            "outbound_comments": null,
            "is_ok": null,
            "status": "IN_PROGRESS",
            "route_password": "28467362",
            "created_at": "2025-01-21T23:14:44Z",
            "updated_at": "2025-01-22T02:28:45Z",
            "deleted_at": null
        },
        {
            "id": 76398298,
            "system_id": "id",
            "legacy_id": 76398298,
            "driver_id": 1590393,
            "vehicle_number": null,
            "zone_id": 28222,
            "hub_id": 1344,
            "datetime": "2025-01-21T17:00:00Z",
            "date": "2025-01-22",
            "archived": false,
            "estimated_end_time": null,
            "driver_assign_time": "2025-01-22T02:44:48Z",
            "driver_attendance": -1,
            "route_comments": null,
            "outbound_comments": null,
            "is_ok": null,
            "status": "IN_PROGRESS",
            "route_password": "28467367",
            "created_at": "2025-01-21T23:14:44Z",
            "updated_at": "2025-01-22T02:44:48Z",
            "deleted_at": null
        },
        {
            "id": 76398299,
            "system_id": "id",
            "legacy_id": 76398299,
            "driver_id": 1606516,
            "vehicle_number": null,
            "zone_id": 28226,
            "hub_id": 1344,
            "datetime": "2025-01-21T17:00:00Z",
            "date": "2025-01-22",
            "archived": false,
            "estimated_end_time": null,
            "driver_assign_time": "2025-01-22T02:27:52Z",
            "driver_attendance": -1,
            "route_comments": null,
            "outbound_comments": null,
            "is_ok": null,
            "status": "IN_PROGRESS",
            "route_password": "28467366",
            "created_at": "2025-01-21T23:14:44Z",
            "updated_at": "2025-01-22T02:27:52Z",
            "deleted_at": null
        },
        {
            "id": 76398300,
            "system_id": "id",
            "legacy_id": 76398300,
            "driver_id": 1607133,
            "vehicle_number": null,
            "zone_id": 28220,
            "hub_id": 1344,
            "datetime": "2025-01-21T17:00:00Z",
            "date": "2025-01-22",
            "archived": false,
            "estimated_end_time": null,
            "driver_assign_time": "2025-01-22T04:50:28Z",
            "driver_attendance": -1,
            "route_comments": null,
            "outbound_comments": null,
            "is_ok": null,
            "status": "IN_PROGRESS",
            "route_password": "28467455",
            "created_at": "2025-01-21T23:14:44Z",
            "updated_at": "2025-01-22T04:50:28Z",
            "deleted_at": null
        },
        {
            "id": 76398301,
            "system_id": "id",
            "legacy_id": 76398301,
            "driver_id": 1607134,
            "vehicle_number": null,
            "zone_id": 28222,
            "hub_id": 1344,
            "datetime": "2025-01-21T17:00:00Z",
            "date": "2025-01-22",
            "archived": false,
            "estimated_end_time": null,
            "driver_assign_time": "2025-01-22T04:02:11Z",
            "driver_attendance": -1,
            "route_comments": null,
            "outbound_comments": null,
            "is_ok": null,
            "status": "IN_PROGRESS",
            "route_password": "28467450",
            "created_at": "2025-01-21T23:14:44Z",
            "updated_at": "2025-01-22T04:02:11Z",
            "deleted_at": null
        },
        {
            "id": 76398302,
            "system_id": "id",
            "legacy_id": 76398302,
            "driver_id": 1622335,
            "vehicle_number": null,
            "zone_id": 28206,
            "hub_id": 1344,
            "datetime": "2025-01-21T17:00:00Z",
            "date": "2025-01-22",
            "archived": false,
            "estimated_end_time": null,
            "driver_assign_time": "2025-01-22T02:08:01Z",
            "driver_attendance": -1,
            "route_comments": null,
            "outbound_comments": null,
            "is_ok": null,
            "status": "IN_PROGRESS",
            "route_password": "28467453",
            "created_at": "2025-01-21T23:14:44Z",
            "updated_at": "2025-01-22T02:08:01Z",
            "deleted_at": null
        },
        {
            "id": 76398303,
            "system_id": "id",
            "legacy_id": 76398303,
            "driver_id": 1648646,
            "vehicle_number": null,
            "zone_id": 28220,
            "hub_id": 1344,
            "datetime": "2025-01-21T17:00:00Z",
            "date": "2025-01-22",
            "archived": false,
            "estimated_end_time": null,
            "driver_assign_time": "2025-01-22T04:39:43Z",
            "driver_attendance": -1,
            "route_comments": null,
            "outbound_comments": null,
            "is_ok": null,
            "status": "IN_PROGRESS",
            "route_password": "28467454",
            "created_at": "2025-01-21T23:14:44Z",
            "updated_at": "2025-01-22T04:39:43Z",
            "deleted_at": null
        },
        {
            "id": 76398305,
            "system_id": "id",
            "legacy_id": 76398305,
            "driver_id": 1663318,
            "vehicle_number": null,
            "zone_id": 28210,
            "hub_id": 1344,
            "datetime": "2025-01-21T17:00:00Z",
            "date": "2025-01-22",
            "archived": false,
            "estimated_end_time": null,
            "driver_assign_time": "2025-01-22T04:01:37Z",
            "driver_attendance": -1,
            "route_comments": null,
            "outbound_comments": null,
            "is_ok": null,
            "status": "IN_PROGRESS",
            "route_password": "28467451",
            "created_at": "2025-01-21T23:14:44Z",
            "updated_at": "2025-01-22T04:01:37Z",
            "deleted_at": null
        },
        {
            "id": 76398307,
            "system_id": "id",
            "legacy_id": 76398307,
            "driver_id": 1668180,
            "vehicle_number": null,
            "zone_id": 28230,
            "hub_id": 1344,
            "datetime": "2025-01-21T17:00:00Z",
            "date": "2025-01-22",
            "archived": false,
            "estimated_end_time": null,
            "driver_assign_time": "2025-01-22T04:46:45Z",
            "driver_attendance": -1,
            "route_comments": null,
            "outbound_comments": null,
            "is_ok": null,
            "status": "IN_PROGRESS",
            "route_password": "28467452",
            "created_at": "2025-01-21T23:14:45Z",
            "updated_at": "2025-01-22T04:46:45Z",
            "deleted_at": null
        },
        {
            "id": 76398310,
            "system_id": "id",
            "legacy_id": 76398310,
            "driver_id": 1676399,
            "vehicle_number": null,
            "zone_id": 28226,
            "hub_id": 1344,
            "datetime": "2025-01-21T17:00:00Z",
            "date": "2025-01-22",
            "archived": false,
            "estimated_end_time": null,
            "driver_assign_time": "2025-01-22T02:31:28Z",
            "driver_attendance": -1,
            "route_comments": null,
            "outbound_comments": null,
            "is_ok": null,
            "status": "IN_PROGRESS",
            "route_password": "28467405",
            "created_at": "2025-01-21T23:14:45Z",
            "updated_at": "2025-01-22T02:31:28Z",
            "deleted_at": null
        },
        {
            "id": 76398311,
            "system_id": "id",
            "legacy_id": 76398311,
            "driver_id": 1678597,
            "vehicle_number": null,
            "zone_id": 28238,
            "hub_id": 1344,
            "datetime": "2025-01-21T17:00:00Z",
            "date": "2025-01-22",
            "archived": false,
            "estimated_end_time": null,
            "driver_assign_time": "2025-01-22T02:01:47Z",
            "driver_attendance": -1,
            "route_comments": null,
            "outbound_comments": null,
            "is_ok": null,
            "status": "IN_PROGRESS",
            "route_password": "28467400",
            "created_at": "2025-01-21T23:14:45Z",
            "updated_at": "2025-01-22T02:01:47Z",
            "deleted_at": null
        },
        {
            "id": 76398316,
            "system_id": "id",
            "legacy_id": 76398316,
            "driver_id": 1726598,
            "vehicle_number": null,
            "zone_id": 28236,
            "hub_id": 1344,
            "datetime": "2025-01-21T17:00:00Z",
            "date": "2025-01-22",
            "archived": false,
            "estimated_end_time": null,
            "driver_assign_time": "2025-01-22T05:37:32Z",
            "driver_attendance": -1,
            "route_comments": null,
            "outbound_comments": null,
            "is_ok": null,
            "status": "IN_PROGRESS",
            "route_password": "28467408",
            "created_at": "2025-01-21T23:14:45Z",
            "updated_at": "2025-01-22T05:37:32Z",
            "deleted_at": null
        },
        {
            "id": 76398323,
            "system_id": "id",
            "legacy_id": 76398323,
            "driver_id": 1682940,
            "vehicle_number": null,
            "zone_id": 28230,
            "hub_id": 1344,
            "datetime": "2025-01-21T17:00:00Z",
            "date": "2025-01-22",
            "archived": false,
            "estimated_end_time": null,
            "driver_assign_time": null,
            "driver_attendance": -1,
            "route_comments": null,
            "outbound_comments": null,
            "is_ok": null,
            "status": "PENDING",
            "route_password": "28467434",
            "created_at": "2025-01-21T23:14:45Z",
            "updated_at": "2025-01-21T23:14:45Z",
            "deleted_at": null
        },
        {
            "id": 76398328,
            "system_id": "id",
            "legacy_id": 76398328,
            "driver_id": 1686142,
            "vehicle_number": null,
            "zone_id": 28222,
            "hub_id": 1344,
            "datetime": "2025-01-21T17:00:00Z",
            "date": "2025-01-22",
            "archived": false,
            "estimated_end_time": null,
            "driver_assign_time": "2025-01-22T06:05:19Z",
            "driver_attendance": -1,
            "route_comments": null,
            "outbound_comments": null,
            "is_ok": null,
            "status": "IN_PROGRESS",
            "route_password": "28467437",
            "created_at": "2025-01-21T23:14:45Z",
            "updated_at": "2025-01-22T06:05:19Z",
            "deleted_at": null
        },
        {
            "id": 76398331,
            "system_id": "id",
            "legacy_id": 76398331,
            "driver_id": 1686518,
            "vehicle_number": null,
            "zone_id": 28234,
            "hub_id": 1344,
            "datetime": "2025-01-21T17:00:00Z",
            "date": "2025-01-22",
            "archived": false,
            "estimated_end_time": null,
            "driver_assign_time": "2025-01-22T04:04:20Z",
            "driver_attendance": -1,
            "route_comments": null,
            "outbound_comments": null,
            "is_ok": null,
            "status": "IN_PROGRESS",
            "route_password": "28467440",
            "created_at": "2025-01-21T23:14:45Z",
            "updated_at": "2025-01-22T04:04:20Z",
            "deleted_at": null
        },
        {
            "id": 76398335,
            "system_id": "id",
            "legacy_id": 76398335,
            "driver_id": 1690774,
            "vehicle_number": null,
            "zone_id": 28236,
            "hub_id": 1344,
            "datetime": "2025-01-21T17:00:00Z",
            "date": "2025-01-22",
            "archived": false,
            "estimated_end_time": null,
            "driver_assign_time": "2025-01-22T05:31:28Z",
            "driver_attendance": -1,
            "route_comments": null,
            "outbound_comments": null,
            "is_ok": null,
            "status": "IN_PROGRESS",
            "route_password": "28467441",
            "created_at": "2025-01-21T23:14:46Z",
            "updated_at": "2025-01-22T05:31:28Z",
            "deleted_at": null
        },
        {
            "id": 76398338,
            "system_id": "id",
            "legacy_id": 76398338,
            "driver_id": 1697951,
            "vehicle_number": null,
            "zone_id": 28218,
            "hub_id": 1344,
            "datetime": "2025-01-21T17:00:00Z",
            "date": "2025-01-22",
            "archived": false,
            "estimated_end_time": null,
            "driver_assign_time": "2025-01-22T03:02:51Z",
            "driver_attendance": -1,
            "route_comments": null,
            "outbound_comments": null,
            "is_ok": null,
            "status": "IN_PROGRESS",
            "route_password": "28467447",
            "created_at": "2025-01-21T23:14:46Z",
            "updated_at": "2025-01-22T03:02:51Z",
            "deleted_at": null
        },
        {
            "id": 76398342,
            "system_id": "id",
            "legacy_id": 76398342,
            "driver_id": 1698082,
            "vehicle_number": null,
            "zone_id": 28240,
            "hub_id": 1344,
            "datetime": "2025-01-21T17:00:00Z",
            "date": "2025-01-22",
            "archived": false,
            "estimated_end_time": null,
            "driver_assign_time": "2025-01-22T05:08:36Z",
            "driver_attendance": -1,
            "route_comments": null,
            "outbound_comments": null,
            "is_ok": null,
            "status": "IN_PROGRESS",
            "route_password": "28467493",
            "created_at": "2025-01-21T23:14:46Z",
            "updated_at": "2025-01-22T05:08:36Z",
            "deleted_at": null
        },
        {
            "id": 76398345,
            "system_id": "id",
            "legacy_id": 76398345,
            "driver_id": 1698618,
            "vehicle_number": null,
            "zone_id": 28216,
            "hub_id": 1344,
            "datetime": "2025-01-21T17:00:00Z",
            "date": "2025-01-22",
            "archived": false,
            "estimated_end_time": null,
            "driver_assign_time": "2025-01-22T04:49:48Z",
            "driver_attendance": -1,
            "route_comments": null,
            "outbound_comments": null,
            "is_ok": null,
            "status": "IN_PROGRESS",
            "route_password": "28467491",
            "created_at": "2025-01-21T23:14:46Z",
            "updated_at": "2025-01-22T04:49:48Z",
            "deleted_at": null
        },
        {
            "id": 76398346,
            "system_id": "id",
            "legacy_id": 76398346,
            "driver_id": 1699173,
            "vehicle_number": null,
            "zone_id": 28214,
            "hub_id": 1344,
            "datetime": "2025-01-21T17:00:00Z",
            "date": "2025-01-22",
            "archived": false,
            "estimated_end_time": null,
            "driver_assign_time": "2025-01-22T06:12:10Z",
            "driver_attendance": -1,
            "route_comments": null,
            "outbound_comments": null,
            "is_ok": null,
            "status": "IN_PROGRESS",
            "route_password": "28467498",
            "created_at": "2025-01-21T23:14:46Z",
            "updated_at": "2025-01-22T06:12:10Z",
            "deleted_at": null
        },
        {
            "id": 76398347,
            "system_id": "id",
            "legacy_id": 76398347,
            "driver_id": 1699670,
            "vehicle_number": null,
            "zone_id": 28218,
            "hub_id": 1344,
            "datetime": "2025-01-21T17:00:00Z",
            "date": "2025-01-22",
            "archived": false,
            "estimated_end_time": null,
            "driver_assign_time": "2025-01-22T02:40:50Z",
            "driver_attendance": -1,
            "route_comments": null,
            "outbound_comments": null,
            "is_ok": null,
            "status": "IN_PROGRESS",
            "route_password": "28467492",
            "created_at": "2025-01-21T23:14:46Z",
            "updated_at": "2025-01-22T02:40:50Z",
            "deleted_at": null
        },
        {
            "id": 76398348,
            "system_id": "id",
            "legacy_id": 76398348,
            "driver_id": 1699897,
            "vehicle_number": null,
            "zone_id": 28224,
            "hub_id": 1344,
            "datetime": "2025-01-21T17:00:00Z",
            "date": "2025-01-22",
            "archived": false,
            "estimated_end_time": null,
            "driver_assign_time": "2025-01-22T02:25:54Z",
            "driver_attendance": -1,
            "route_comments": null,
            "outbound_comments": null,
            "is_ok": null,
            "status": "IN_PROGRESS",
            "route_password": "28467497",
            "created_at": "2025-01-21T23:14:46Z",
            "updated_at": "2025-01-22T02:25:54Z",
            "deleted_at": null
        },
        {
            "id": 76398350,
            "system_id": "id",
            "legacy_id": 76398350,
            "driver_id": 1700451,
            "vehicle_number": null,
            "zone_id": 28240,
            "hub_id": 1344,
            "datetime": "2025-01-21T17:00:00Z",
            "date": "2025-01-22",
            "archived": false,
            "estimated_end_time": null,
            "driver_assign_time": "2025-01-22T03:26:55Z",
            "driver_attendance": -1,
            "route_comments": null,
            "outbound_comments": null,
            "is_ok": null,
            "status": "IN_PROGRESS",
            "route_password": "28467415",
            "created_at": "2025-01-21T23:14:47Z",
            "updated_at": "2025-01-22T03:26:55Z",
            "deleted_at": null
        },
        {
            "id": 76398351,
            "system_id": "id",
            "legacy_id": 76398351,
            "driver_id": 1700595,
            "vehicle_number": null,
            "zone_id": 28238,
            "hub_id": 1344,
            "datetime": "2025-01-21T17:00:00Z",
            "date": "2025-01-22",
            "archived": false,
            "estimated_end_time": null,
            "driver_assign_time": "2025-01-22T02:28:10Z",
            "driver_attendance": -1,
            "route_comments": null,
            "outbound_comments": null,
            "is_ok": null,
            "status": "IN_PROGRESS",
            "route_password": "28467410",
            "created_at": "2025-01-21T23:14:47Z",
            "updated_at": "2025-01-22T02:28:10Z",
            "deleted_at": null
        },
        {
            "id": 76398352,
            "system_id": "id",
            "legacy_id": 76398352,
            "driver_id": 1701007,
            "vehicle_number": null,
            "zone_id": 28210,
            "hub_id": 1344,
            "datetime": "2025-01-21T17:00:00Z",
            "date": "2025-01-22",
            "archived": false,
            "estimated_end_time": null,
            "driver_assign_time": "2025-01-22T02:41:00Z",
            "driver_attendance": -1,
            "route_comments": null,
            "outbound_comments": null,
            "is_ok": null,
            "status": "IN_PROGRESS",
            "route_password": "28467413",
            "created_at": "2025-01-21T23:14:47Z",
            "updated_at": "2025-01-22T02:41:00Z",
            "deleted_at": null
        },
        {
            "id": 76398353,
            "system_id": "id",
            "legacy_id": 76398353,
            "driver_id": 1701049,
            "vehicle_number": null,
            "zone_id": 28210,
            "hub_id": 1344,
            "datetime": "2025-01-21T17:00:00Z",
            "date": "2025-01-22",
            "archived": false,
            "estimated_end_time": null,
            "driver_assign_time": "2025-01-22T04:03:52Z",
            "driver_attendance": -1,
            "route_comments": null,
            "outbound_comments": null,
            "is_ok": null,
            "status": "IN_PROGRESS",
            "route_password": "28467414",
            "created_at": "2025-01-21T23:14:47Z",
            "updated_at": "2025-01-22T04:03:52Z",
            "deleted_at": null
        },
        {
            "id": 76398354,
            "system_id": "id",
            "legacy_id": 76398354,
            "driver_id": 1701050,
            "vehicle_number": null,
            "zone_id": 28234,
            "hub_id": 1344,
            "datetime": "2025-01-21T17:00:00Z",
            "date": "2025-01-22",
            "archived": false,
            "estimated_end_time": null,
            "driver_assign_time": "2025-01-22T03:57:53Z",
            "driver_attendance": -1,
            "route_comments": null,
            "outbound_comments": null,
            "is_ok": null,
            "status": "IN_PROGRESS",
            "route_password": "28467419",
            "created_at": "2025-01-21T23:14:47Z",
            "updated_at": "2025-01-22T03:57:53Z",
            "deleted_at": null
        },
        {
            "id": 76398355,
            "system_id": "id",
            "legacy_id": 76398355,
            "driver_id": 1701060,
            "vehicle_number": null,
            "zone_id": 28224,
            "hub_id": 1344,
            "datetime": "2025-01-21T17:00:00Z",
            "date": "2025-01-22",
            "archived": false,
            "estimated_end_time": null,
            "driver_assign_time": "2025-01-22T06:07:01Z",
            "driver_attendance": -1,
            "route_comments": null,
            "outbound_comments": null,
            "is_ok": null,
            "status": "IN_PROGRESS",
            "route_password": "28467411",
            "created_at": "2025-01-21T23:14:47Z",
            "updated_at": "2025-01-22T06:07:01Z",
            "deleted_at": null
        },
        {
            "id": 76398356,
            "system_id": "id",
            "legacy_id": 76398356,
            "driver_id": 1701062,
            "vehicle_number": null,
            "zone_id": 28226,
            "hub_id": 1344,
            "datetime": "2025-01-21T17:00:00Z",
            "date": "2025-01-22",
            "archived": false,
            "estimated_end_time": null,
            "driver_assign_time": null,
            "driver_attendance": -1,
            "route_comments": null,
            "outbound_comments": null,
            "is_ok": null,
            "status": "PENDING",
            "route_password": "28467418",
            "created_at": "2025-01-21T23:14:47Z",
            "updated_at": "2025-01-21T23:14:47Z",
            "deleted_at": null
        },
        {
            "id": 76398357,
            "system_id": "id",
            "legacy_id": 76398357,
            "driver_id": 1701900,
            "vehicle_number": null,
            "zone_id": 28216,
            "hub_id": 1344,
            "datetime": "2025-01-21T17:00:00Z",
            "date": "2025-01-22",
            "archived": false,
            "estimated_end_time": null,
            "driver_assign_time": "2025-01-22T05:34:19Z",
            "driver_attendance": -1,
            "route_comments": null,
            "outbound_comments": null,
            "is_ok": null,
            "status": "IN_PROGRESS",
            "route_password": "28467412",
            "created_at": "2025-01-21T23:14:47Z",
            "updated_at": "2025-01-22T05:34:19Z",
            "deleted_at": null
        },
        {
            "id": 76398358,
            "system_id": "id",
            "legacy_id": 76398358,
            "driver_id": 1701910,
            "vehicle_number": null,
            "zone_id": 28228,
            "hub_id": 1344,
            "datetime": "2025-01-21T17:00:00Z",
            "date": "2025-01-22",
            "archived": false,
            "estimated_end_time": null,
            "driver_assign_time": "2025-01-22T03:58:11Z",
            "driver_attendance": -1,
            "route_comments": null,
            "outbound_comments": null,
            "is_ok": null,
            "status": "IN_PROGRESS",
            "route_password": "28467417",
            "created_at": "2025-01-21T23:14:48Z",
            "updated_at": "2025-01-22T03:58:11Z",
            "deleted_at": null
        },
        {
            "id": 76398360,
            "system_id": "id",
            "legacy_id": 76398360,
            "driver_id": 1702007,
            "vehicle_number": null,
            "zone_id": 28214,
            "hub_id": 1344,
            "datetime": "2025-01-21T17:00:00Z",
            "date": "2025-01-22",
            "archived": false,
            "estimated_end_time": null,
            "driver_assign_time": null,
            "driver_attendance": -1,
            "route_comments": null,
            "outbound_comments": null,
            "is_ok": null,
            "status": "PENDING",
            "route_password": "28467485",
            "created_at": "2025-01-21T23:14:48Z",
            "updated_at": "2025-01-21T23:14:48Z",
            "deleted_at": null
        },
        {
            "id": 76398361,
            "system_id": "id",
            "legacy_id": 76398361,
            "driver_id": 1702037,
            "vehicle_number": null,
            "zone_id": 28230,
            "hub_id": 1344,
            "datetime": "2025-01-21T17:00:00Z",
            "date": "2025-01-22",
            "archived": false,
            "estimated_end_time": null,
            "driver_assign_time": "2025-01-22T03:42:31Z",
            "driver_attendance": -1,
            "route_comments": null,
            "outbound_comments": null,
            "is_ok": null,
            "status": "IN_PROGRESS",
            "route_password": "28467480",
            "created_at": "2025-01-21T23:14:48Z",
            "updated_at": "2025-01-22T03:42:31Z",
            "deleted_at": null
        },
        {
            "id": 76398362,
            "system_id": "id",
            "legacy_id": 76398362,
            "driver_id": 1702101,
            "vehicle_number": null,
            "zone_id": 28206,
            "hub_id": 1344,
            "datetime": "2025-01-21T17:00:00Z",
            "date": "2025-01-22",
            "archived": false,
            "estimated_end_time": null,
            "driver_assign_time": null,
            "driver_attendance": -1,
            "route_comments": null,
            "outbound_comments": null,
            "is_ok": null,
            "status": "PENDING",
            "route_password": "28467483",
            "created_at": "2025-01-21T23:14:48Z",
            "updated_at": "2025-01-21T23:14:48Z",
            "deleted_at": null
        },
        {
            "id": 76398363,
            "system_id": "id",
            "legacy_id": 76398363,
            "driver_id": 1702103,
            "vehicle_number": null,
            "zone_id": 28242,
            "hub_id": 1344,
            "datetime": "2025-01-21T17:00:00Z",
            "date": "2025-01-22",
            "archived": false,
            "estimated_end_time": null,
            "driver_assign_time": "2025-01-22T04:35:05Z",
            "driver_attendance": -1,
            "route_comments": null,
            "outbound_comments": null,
            "is_ok": null,
            "status": "IN_PROGRESS",
            "route_password": "28467484",
            "created_at": "2025-01-21T23:14:48Z",
            "updated_at": "2025-01-22T04:35:05Z",
            "deleted_at": null
        },
        {
            "id": 76398367,
            "system_id": "id",
            "legacy_id": 76398367,
            "driver_id": 1705417,
            "vehicle_number": null,
            "zone_id": 28232,
            "hub_id": 1344,
            "datetime": "2025-01-21T17:00:00Z",
            "date": "2025-01-22",
            "archived": false,
            "estimated_end_time": null,
            "driver_assign_time": "2025-01-22T05:40:48Z",
            "driver_attendance": -1,
            "route_comments": null,
            "outbound_comments": null,
            "is_ok": null,
            "status": "IN_PROGRESS",
            "route_password": "28467482",
            "created_at": "2025-01-21T23:14:48Z",
            "updated_at": "2025-01-22T05:40:48Z",
            "deleted_at": null
        },
        {
            "id": 76398368,
            "system_id": "id",
            "legacy_id": 76398368,
            "driver_id": 1706973,
            "vehicle_number": null,
            "zone_id": 28228,
            "hub_id": 1344,
            "datetime": "2025-01-21T17:00:00Z",
            "date": "2025-01-22",
            "archived": false,
            "estimated_end_time": null,
            "driver_assign_time": "2025-01-22T02:37:00Z",
            "driver_attendance": -1,
            "route_comments": null,
            "outbound_comments": null,
            "is_ok": null,
            "status": "IN_PROGRESS",
            "route_password": "28467487",
            "created_at": "2025-01-21T23:14:49Z",
            "updated_at": "2025-01-22T02:37:00Z",
            "deleted_at": null
        },
        {
            "id": 76398369,
            "system_id": "id",
            "legacy_id": 76398369,
            "driver_id": 1707342,
            "vehicle_number": null,
            "zone_id": 28214,
            "hub_id": 1344,
            "datetime": "2025-01-21T17:00:00Z",
            "date": "2025-01-22",
            "archived": false,
            "estimated_end_time": null,
            "driver_assign_time": "2025-01-22T06:10:05Z",
            "driver_attendance": -1,
            "route_comments": null,
            "outbound_comments": null,
            "is_ok": null,
            "status": "IN_PROGRESS",
            "route_password": "28467486",
            "created_at": "2025-01-21T23:14:49Z",
            "updated_at": "2025-01-22T06:10:05Z",
            "deleted_at": null
        },
        {
            "id": 76398370,
            "system_id": "id",
            "legacy_id": 76398370,
            "driver_id": 1737641,
            "vehicle_number": null,
            "zone_id": 28214,
            "hub_id": 1344,
            "datetime": "2025-01-21T17:00:00Z",
            "date": "2025-01-22",
            "archived": false,
            "estimated_end_time": null,
            "driver_assign_time": null,
            "driver_attendance": -1,
            "route_comments": null,
            "outbound_comments": null,
            "is_ok": null,
            "status": "PENDING",
            "route_password": "28467425",
            "created_at": "2025-01-21T23:14:49Z",
            "updated_at": "2025-01-22T06:01:58Z",
            "deleted_at": null
        },
        {
            "id": 76398372,
            "system_id": "id",
            "legacy_id": 76398372,
            "driver_id": 1708873,
            "vehicle_number": null,
            "zone_id": 28220,
            "hub_id": 1344,
            "datetime": "2025-01-21T17:00:00Z",
            "date": "2025-01-22",
            "archived": false,
            "estimated_end_time": null,
            "driver_assign_time": "2025-01-22T05:01:30Z",
            "driver_attendance": -1,
            "route_comments": null,
            "outbound_comments": null,
            "is_ok": null,
            "status": "IN_PROGRESS",
            "route_password": "28467423",
            "created_at": "2025-01-21T23:14:49Z",
            "updated_at": "2025-01-22T05:01:30Z",
            "deleted_at": null
        },
        {
            "id": 76398373,
            "system_id": "id",
            "legacy_id": 76398373,
            "driver_id": 1716205,
            "vehicle_number": null,
            "zone_id": 28226,
            "hub_id": 1344,
            "datetime": "2025-01-21T17:00:00Z",
            "date": "2025-01-22",
            "archived": false,
            "estimated_end_time": null,
            "driver_assign_time": "2025-01-22T03:49:32Z",
            "driver_attendance": -1,
            "route_comments": null,
            "outbound_comments": null,
            "is_ok": null,
            "status": "IN_PROGRESS",
            "route_password": "28467424",
            "created_at": "2025-01-21T23:14:49Z",
            "updated_at": "2025-01-22T03:49:32Z",
            "deleted_at": null
        },
        {
            "id": 76398374,
            "system_id": "id",
            "legacy_id": 76398374,
            "driver_id": 1716934,
            "vehicle_number": null,
            "zone_id": 28210,
            "hub_id": 1344,
            "datetime": "2025-01-21T17:00:00Z",
            "date": "2025-01-22",
            "archived": false,
            "estimated_end_time": null,
            "driver_assign_time": "2025-01-22T02:44:02Z",
            "driver_attendance": -1,
            "route_comments": null,
            "outbound_comments": null,
            "is_ok": null,
            "status": "IN_PROGRESS",
            "route_password": "28467429",
            "created_at": "2025-01-21T23:14:49Z",
            "updated_at": "2025-01-22T02:44:02Z",
            "deleted_at": null
        },
        {
            "id": 76398375,
            "system_id": "id",
            "legacy_id": 76398375,
            "driver_id": 1718454,
            "vehicle_number": null,
            "zone_id": 28236,
            "hub_id": 1344,
            "datetime": "2025-01-21T17:00:00Z",
            "date": "2025-01-22",
            "archived": false,
            "estimated_end_time": null,
            "driver_assign_time": "2025-01-22T02:35:30Z",
            "driver_attendance": -1,
            "route_comments": null,
            "outbound_comments": null,
            "is_ok": null,
            "status": "IN_PROGRESS",
            "route_password": "28467421",
            "created_at": "2025-01-21T23:14:49Z",
            "updated_at": "2025-01-22T02:35:30Z",
            "deleted_at": null
        },
        {
            "id": 76398376,
            "system_id": "id",
            "legacy_id": 76398376,
            "driver_id": 1718508,
            "vehicle_number": null,
            "zone_id": 28222,
            "hub_id": 1344,
            "datetime": "2025-01-21T17:00:00Z",
            "date": "2025-01-22",
            "archived": false,
            "estimated_end_time": null,
            "driver_assign_time": null,
            "driver_attendance": -1,
            "route_comments": null,
            "outbound_comments": null,
            "is_ok": null,
            "status": "PENDING",
            "route_password": "28467428",
            "created_at": "2025-01-21T23:14:50Z",
            "updated_at": "2025-01-21T23:14:50Z",
            "deleted_at": null
        },
        {
            "id": 76398377,
            "system_id": "id",
            "legacy_id": 76398377,
            "driver_id": 1719524,
            "vehicle_number": null,
            "zone_id": 28226,
            "hub_id": 1344,
            "datetime": "2025-01-21T17:00:00Z",
            "date": "2025-01-22",
            "archived": false,
            "estimated_end_time": null,
            "driver_assign_time": "2025-01-22T05:52:44Z",
            "driver_attendance": -1,
            "route_comments": null,
            "outbound_comments": null,
            "is_ok": null,
            "status": "IN_PROGRESS",
            "route_password": "28467422",
            "created_at": "2025-01-21T23:14:50Z",
            "updated_at": "2025-01-22T05:52:44Z",
            "deleted_at": null
        },
        {
            "id": 76398378,
            "system_id": "id",
            "legacy_id": 76398378,
            "driver_id": 1719778,
            "vehicle_number": null,
            "zone_id": 28230,
            "hub_id": 1344,
            "datetime": "2025-01-21T17:00:00Z",
            "date": "2025-01-22",
            "archived": false,
            "estimated_end_time": null,
            "driver_assign_time": null,
            "driver_attendance": -1,
            "route_comments": null,
            "outbound_comments": null,
            "is_ok": null,
            "status": "PENDING",
            "route_password": "28467427",
            "created_at": "2025-01-21T23:14:50Z",
            "updated_at": "2025-01-21T23:14:50Z",
            "deleted_at": null
        },
        {
            "id": 76398379,
            "system_id": "id",
            "legacy_id": 76398379,
            "driver_id": 1719807,
            "vehicle_number": null,
            "zone_id": 28212,
            "hub_id": 1344,
            "datetime": "2025-01-21T17:00:00Z",
            "date": "2025-01-22",
            "archived": false,
            "estimated_end_time": null,
            "driver_assign_time": "2025-01-22T02:19:38Z",
            "driver_attendance": -1,
            "route_comments": null,
            "outbound_comments": null,
            "is_ok": null,
            "status": "IN_PROGRESS",
            "route_password": "28467426",
            "created_at": "2025-01-21T23:14:50Z",
            "updated_at": "2025-01-22T02:19:38Z",
            "deleted_at": null
        },
        {
            "id": 76398380,
            "system_id": "id",
            "legacy_id": 76398380,
            "driver_id": 1719809,
            "vehicle_number": null,
            "zone_id": 28216,
            "hub_id": 1344,
            "datetime": "2025-01-21T17:00:00Z",
            "date": "2025-01-22",
            "archived": false,
            "estimated_end_time": null,
            "driver_assign_time": "2025-01-22T05:36:17Z",
            "driver_attendance": -1,
            "route_comments": null,
            "outbound_comments": null,
            "is_ok": null,
            "status": "IN_PROGRESS",
            "route_password": "28467475",
            "created_at": "2025-01-21T23:14:50Z",
            "updated_at": "2025-01-22T05:36:17Z",
            "deleted_at": null
        },
        {
            "id": 76398381,
            "system_id": "id",
            "legacy_id": 76398381,
            "driver_id": 1720782,
            "vehicle_number": null,
            "zone_id": 28210,
            "hub_id": 1344,
            "datetime": "2025-01-21T17:00:00Z",
            "date": "2025-01-22",
            "archived": false,
            "estimated_end_time": null,
            "driver_assign_time": "2025-01-22T02:45:36Z",
            "driver_attendance": -1,
            "route_comments": null,
            "outbound_comments": null,
            "is_ok": null,
            "status": "IN_PROGRESS",
            "route_password": "28467470",
            "created_at": "2025-01-21T23:14:50Z",
            "updated_at": "2025-01-22T02:45:36Z",
            "deleted_at": null
        },
        {
            "id": 76398382,
            "system_id": "id",
            "legacy_id": 76398382,
            "driver_id": 1720927,
            "vehicle_number": null,
            "zone_id": 28226,
            "hub_id": 1344,
            "datetime": "2025-01-21T17:00:00Z",
            "date": "2025-01-22",
            "archived": false,
            "estimated_end_time": null,
            "driver_assign_time": "2025-01-22T06:00:31Z",
            "driver_attendance": -1,
            "route_comments": null,
            "outbound_comments": null,
            "is_ok": null,
            "status": "IN_PROGRESS",
            "route_password": "28467473",
            "created_at": "2025-01-21T23:14:50Z",
            "updated_at": "2025-01-22T06:00:31Z",
            "deleted_at": null
        },
        {
            "id": 76398383,
            "system_id": "id",
            "legacy_id": 76398383,
            "driver_id": 1720990,
            "vehicle_number": null,
            "zone_id": 28228,
            "hub_id": 1344,
            "datetime": "2025-01-21T17:00:00Z",
            "date": "2025-01-22",
            "archived": false,
            "estimated_end_time": null,
            "driver_assign_time": null,
            "driver_attendance": -1,
            "route_comments": null,
            "outbound_comments": null,
            "is_ok": null,
            "status": "PENDING",
            "route_password": "28467474",
            "created_at": "2025-01-21T23:14:50Z",
            "updated_at": "2025-01-21T23:14:50Z",
            "deleted_at": null
        },
        {
            "id": 76398385,
            "system_id": "id",
            "legacy_id": 76398385,
            "driver_id": 1721149,
            "vehicle_number": null,
            "zone_id": 28242,
            "hub_id": 1344,
            "datetime": "2025-01-21T17:00:00Z",
            "date": "2025-01-22",
            "archived": false,
            "estimated_end_time": null,
            "driver_assign_time": "2025-01-22T04:25:26Z",
            "driver_attendance": -1,
            "route_comments": null,
            "outbound_comments": null,
            "is_ok": null,
            "status": "IN_PROGRESS",
            "route_password": "28467471",
            "created_at": "2025-01-21T23:14:51Z",
            "updated_at": "2025-01-22T04:25:26Z",
            "deleted_at": null
        },
        {
            "id": 76398386,
            "system_id": "id",
            "legacy_id": 76398386,
            "driver_id": 1721201,
            "vehicle_number": null,
            "zone_id": 28230,
            "hub_id": 1344,
            "datetime": "2025-01-21T17:00:00Z",
            "date": "2025-01-22",
            "archived": false,
            "estimated_end_time": null,
            "driver_assign_time": null,
            "driver_attendance": -1,
            "route_comments": null,
            "outbound_comments": null,
            "is_ok": null,
            "status": "PENDING",
            "route_password": "28467478",
            "created_at": "2025-01-21T23:14:51Z",
            "updated_at": "2025-01-21T23:14:51Z",
            "deleted_at": null
        },
        {
            "id": 76398388,
            "system_id": "id",
            "legacy_id": 76398388,
            "driver_id": 1722761,
            "vehicle_number": null,
            "zone_id": 28236,
            "hub_id": 1344,
            "datetime": "2025-01-21T17:00:00Z",
            "date": "2025-01-22",
            "archived": false,
            "estimated_end_time": null,
            "driver_assign_time": "2025-01-22T02:38:44Z",
            "driver_attendance": -1,
            "route_comments": null,
            "outbound_comments": null,
            "is_ok": null,
            "status": "IN_PROGRESS",
            "route_password": "28467477",
            "created_at": "2025-01-21T23:14:51Z",
            "updated_at": "2025-01-22T02:38:44Z",
            "deleted_at": null
        },
        {
            "id": 76398389,
            "system_id": "id",
            "legacy_id": 76398389,
            "driver_id": 1724070,
            "vehicle_number": null,
            "zone_id": 28244,
            "hub_id": 1344,
            "datetime": "2025-01-21T17:00:00Z",
            "date": "2025-01-22",
            "archived": false,
            "estimated_end_time": null,
            "driver_assign_time": "2025-01-22T04:31:12Z",
            "driver_attendance": -1,
            "route_comments": null,
            "outbound_comments": null,
            "is_ok": null,
            "status": "IN_PROGRESS",
            "route_password": "28467476",
            "created_at": "2025-01-21T23:14:51Z",
            "updated_at": "2025-01-22T04:31:12Z",
            "deleted_at": null
        },
        {
            "id": 76398390,
            "system_id": "id",
            "legacy_id": 76398390,
            "driver_id": 1724075,
            "vehicle_number": null,
            "zone_id": 28228,
            "hub_id": 1344,
            "datetime": "2025-01-21T17:00:00Z",
            "date": "2025-01-22",
            "archived": false,
            "estimated_end_time": null,
            "driver_assign_time": "2025-01-22T06:08:07Z",
            "driver_attendance": -1,
            "route_comments": null,
            "outbound_comments": null,
            "is_ok": null,
            "status": "IN_PROGRESS",
            "route_password": "28467465",
            "created_at": "2025-01-21T23:14:51Z",
            "updated_at": "2025-01-22T06:08:07Z",
            "deleted_at": null
        },
        {
            "id": 76398391,
            "system_id": "id",
            "legacy_id": 76398391,
            "driver_id": 1724864,
            "vehicle_number": null,
            "zone_id": 28222,
            "hub_id": 1344,
            "datetime": "2025-01-21T17:00:00Z",
            "date": "2025-01-22",
            "archived": false,
            "estimated_end_time": null,
            "driver_assign_time": "2025-01-22T06:06:12Z",
            "driver_attendance": -1,
            "route_comments": null,
            "outbound_comments": null,
            "is_ok": null,
            "status": "IN_PROGRESS",
            "route_password": "28467460",
            "created_at": "2025-01-21T23:14:51Z",
            "updated_at": "2025-01-22T06:06:12Z",
            "deleted_at": null
        },
        {
            "id": 76398392,
            "system_id": "id",
            "legacy_id": 76398392,
            "driver_id": 1726590,
            "vehicle_number": null,
            "zone_id": 28214,
            "hub_id": 1344,
            "datetime": "2025-01-21T17:00:00Z",
            "date": "2025-01-22",
            "archived": false,
            "estimated_end_time": null,
            "driver_assign_time": "2025-01-22T06:05:18Z",
            "driver_attendance": -1,
            "route_comments": null,
            "outbound_comments": null,
            "is_ok": null,
            "status": "IN_PROGRESS",
            "route_password": "28467463",
            "created_at": "2025-01-21T23:14:52Z",
            "updated_at": "2025-01-22T06:05:18Z",
            "deleted_at": null
        },
        {
            "id": 76398393,
            "system_id": "id",
            "legacy_id": 76398393,
            "driver_id": 1726595,
            "vehicle_number": null,
            "zone_id": 28220,
            "hub_id": 1344,
            "datetime": "2025-01-21T17:00:00Z",
            "date": "2025-01-22",
            "archived": false,
            "estimated_end_time": null,
            "driver_assign_time": "2025-01-22T04:57:50Z",
            "driver_attendance": -1,
            "route_comments": null,
            "outbound_comments": null,
            "is_ok": null,
            "status": "IN_PROGRESS",
            "route_password": "28467464",
            "created_at": "2025-01-21T23:14:52Z",
            "updated_at": "2025-01-22T04:57:50Z",
            "deleted_at": null
        },
        {
            "id": 76398396,
            "system_id": "id",
            "legacy_id": 76398396,
            "driver_id": 1727079,
            "vehicle_number": null,
            "zone_id": 28228,
            "hub_id": 1344,
            "datetime": "2025-01-21T17:00:00Z",
            "date": "2025-01-22",
            "archived": false,
            "estimated_end_time": null,
            "driver_assign_time": null,
            "driver_attendance": -1,
            "route_comments": null,
            "outbound_comments": null,
            "is_ok": null,
            "status": "PENDING",
            "route_password": "28467468",
            "created_at": "2025-01-21T23:14:52Z",
            "updated_at": "2025-01-21T23:14:52Z",
            "deleted_at": null
        },
        {
            "id": 76398400,
            "system_id": "id",
            "legacy_id": 76398400,
            "driver_id": 1726589,
            "vehicle_number": null,
            "zone_id": 28222,
            "hub_id": 1344,
            "datetime": "2025-01-21T17:00:00Z",
            "date": "2025-01-22",
            "archived": false,
            "estimated_end_time": null,
            "driver_assign_time": null,
            "driver_attendance": -1,
            "route_comments": null,
            "outbound_comments": null,
            "is_ok": null,
            "status": "PENDING",
            "route_password": "28467955",
            "created_at": "2025-01-21T23:14:53Z",
            "updated_at": "2025-01-21T23:14:53Z",
            "deleted_at": null
        },
        {
            "id": 76398401,
            "system_id": "id",
            "legacy_id": 76398401,
            "driver_id": 1732775,
            "vehicle_number": null,
            "zone_id": 28232,
            "hub_id": 1344,
            "datetime": "2025-01-21T17:00:00Z",
            "date": "2025-01-22",
            "archived": false,
            "estimated_end_time": null,
            "driver_assign_time": "2025-01-22T05:40:00Z",
            "driver_attendance": -1,
            "route_comments": null,
            "outbound_comments": null,
            "is_ok": null,
            "status": "IN_PROGRESS",
            "route_password": "28467950",
            "created_at": "2025-01-21T23:14:53Z",
            "updated_at": "2025-01-22T05:40:00Z",
            "deleted_at": null
        },
        {
            "id": 76398402,
            "system_id": "id",
            "legacy_id": 76398402,
            "driver_id": 1732776,
            "vehicle_number": null,
            "zone_id": 28218,
            "hub_id": 1344,
            "datetime": "2025-01-21T17:00:00Z",
            "date": "2025-01-22",
            "archived": false,
            "estimated_end_time": null,
            "driver_assign_time": "2025-01-22T03:27:11Z",
            "driver_attendance": -1,
            "route_comments": null,
            "outbound_comments": null,
            "is_ok": null,
            "status": "IN_PROGRESS",
            "route_password": "28467953",
            "created_at": "2025-01-21T23:14:53Z",
            "updated_at": "2025-01-22T03:27:11Z",
            "deleted_at": null
        },
        {
            "id": 76398403,
            "system_id": "id",
            "legacy_id": 76398403,
            "driver_id": 1728940,
            "vehicle_number": null,
            "zone_id": 28232,
            "hub_id": 1344,
            "datetime": "2025-01-21T17:00:00Z",
            "date": "2025-01-22",
            "archived": false,
            "estimated_end_time": null,
            "driver_assign_time": "2025-01-22T05:55:24Z",
            "driver_attendance": -1,
            "route_comments": null,
            "outbound_comments": null,
            "is_ok": null,
            "status": "IN_PROGRESS",
            "route_password": "28467954",
            "created_at": "2025-01-21T23:14:53Z",
            "updated_at": "2025-01-22T05:55:24Z",
            "deleted_at": null
        },
        {
            "id": 76398404,
            "system_id": "id",
            "legacy_id": 76398404,
            "driver_id": 1727949,
            "vehicle_number": null,
            "zone_id": 28214,
            "hub_id": 1344,
            "datetime": "2025-01-21T17:00:00Z",
            "date": "2025-01-22",
            "archived": false,
            "estimated_end_time": null,
            "driver_assign_time": null,
            "driver_attendance": -1,
            "route_comments": null,
            "outbound_comments": null,
            "is_ok": null,
            "status": "PENDING",
            "route_password": "28467959",
            "created_at": "2025-01-21T23:14:53Z",
            "updated_at": "2025-01-21T23:14:53Z",
            "deleted_at": null
        },
        {
            "id": 76398406,
            "system_id": "id",
            "legacy_id": 76398406,
            "driver_id": 1623377,
            "vehicle_number": null,
            "zone_id": 28236,
            "hub_id": 1344,
            "datetime": "2025-01-21T17:00:00Z",
            "date": "2025-01-22",
            "archived": false,
            "estimated_end_time": null,
            "driver_assign_time": "2025-01-22T03:53:41Z",
            "driver_attendance": -1,
            "route_comments": null,
            "outbound_comments": null,
            "is_ok": null,
            "status": "IN_PROGRESS",
            "route_password": "28467958",
            "created_at": "2025-01-21T23:14:53Z",
            "updated_at": "2025-01-22T03:53:41Z",
            "deleted_at": null
        },
        {
            "id": 76398407,
            "system_id": "id",
            "legacy_id": 76398407,
            "driver_id": 1730289,
            "vehicle_number": null,
            "zone_id": 28212,
            "hub_id": 1344,
            "datetime": "2025-01-21T17:00:00Z",
            "date": "2025-01-22",
            "archived": false,
            "estimated_end_time": null,
            "driver_assign_time": "2025-01-22T03:01:12Z",
            "driver_attendance": -1,
            "route_comments": null,
            "outbound_comments": null,
            "is_ok": null,
            "status": "IN_PROGRESS",
            "route_password": "28467952",
            "created_at": "2025-01-21T23:14:53Z",
            "updated_at": "2025-01-22T03:01:12Z",
            "deleted_at": null
        },
        {
            "id": 76398409,
            "system_id": "id",
            "legacy_id": 76398409,
            "driver_id": 1728947,
            "vehicle_number": null,
            "zone_id": 28218,
            "hub_id": 1344,
            "datetime": "2025-01-21T17:00:00Z",
            "date": "2025-01-22",
            "archived": false,
            "estimated_end_time": null,
            "driver_assign_time": "2025-01-22T02:38:54Z",
            "driver_attendance": -1,
            "route_comments": null,
            "outbound_comments": null,
            "is_ok": null,
            "status": "IN_PROGRESS",
            "route_password": "28467956",
            "created_at": "2025-01-21T23:14:54Z",
            "updated_at": "2025-01-22T02:38:54Z",
            "deleted_at": null
        },
        {
            "id": 76398410,
            "system_id": "id",
            "legacy_id": 76398410,
            "driver_id": 1728949,
            "vehicle_number": null,
            "zone_id": 28236,
            "hub_id": 1344,
            "datetime": "2025-01-21T17:00:00Z",
            "date": "2025-01-22",
            "archived": false,
            "estimated_end_time": null,
            "driver_assign_time": null,
            "driver_attendance": -1,
            "route_comments": null,
            "outbound_comments": null,
            "is_ok": null,
            "status": "PENDING",
            "route_password": "28467905",
            "created_at": "2025-01-21T23:14:54Z",
            "updated_at": "2025-01-21T23:14:54Z",
            "deleted_at": null
        },
        {
            "id": 76398411,
            "system_id": "id",
            "legacy_id": 76398411,
            "driver_id": 1727953,
            "vehicle_number": null,
            "zone_id": 28226,
            "hub_id": 1344,
            "datetime": "2025-01-21T17:00:00Z",
            "date": "2025-01-22",
            "archived": false,
            "estimated_end_time": null,
            "driver_assign_time": "2025-01-22T02:49:25Z",
            "driver_attendance": -1,
            "route_comments": null,
            "outbound_comments": null,
            "is_ok": null,
            "status": "IN_PROGRESS",
            "route_password": "28467900",
            "created_at": "2025-01-21T23:14:54Z",
            "updated_at": "2025-01-22T02:49:25Z",
            "deleted_at": null
        },
        {
            "id": 76398412,
            "system_id": "id",
            "legacy_id": 76398412,
            "driver_id": 1731711,
            "vehicle_number": null,
            "zone_id": 28220,
            "hub_id": 1344,
            "datetime": "2025-01-21T17:00:00Z",
            "date": "2025-01-22",
            "archived": false,
            "estimated_end_time": null,
            "driver_assign_time": "2025-01-22T04:47:46Z",
            "driver_attendance": -1,
            "route_comments": null,
            "outbound_comments": null,
            "is_ok": null,
            "status": "IN_PROGRESS",
            "route_password": "28467903",
            "created_at": "2025-01-21T23:14:54Z",
            "updated_at": "2025-01-22T04:47:46Z",
            "deleted_at": null
        },
        {
            "id": 76424300,
            "system_id": "id",
            "legacy_id": 76424300,
            "driver_id": 1653650,
            "vehicle_number": null,
            "zone_id": 28232,
            "hub_id": 1344,
            "datetime": "2025-01-21T17:00:00Z",
            "date": "2025-01-22",
            "archived": false,
            "estimated_end_time": null,
            "driver_assign_time": "2025-01-22T04:05:50Z",
            "driver_attendance": -1,
            "route_comments": null,
            "outbound_comments": null,
            "is_ok": null,
            "status": "IN_PROGRESS",
            "route_password": "28939455",
            "created_at": "2025-01-22T04:01:33Z",
            "updated_at": "2025-01-22T04:05:50Z",
            "deleted_at": null
        }
    ]
}
